<?xml version="1.0" encoding="UTF-8" standalone="no"?>
<Levels>
    <Level1>
        <mapSize>20</mapSize>
        <Tile AreaType="SpawnArea">
            <Coordinates>0,0</Coordinates>
        </Tile>
        <Tile AreaType="Path">
            <Coordinates>1,0</Coordinates>
        </Tile>
        <Tile AreaType="Path">
            <Coordinates>2,0</Coordinates>
        </Tile>
        <Tile AreaType="Path">
            <Coordinates>3,0</Coordinates>
        </Tile>
        <Tile AreaType="Path">
            <Coordinates>4,0</Coordinates>
        </Tile>
        <Tile AreaType="Path">
            <Coordinates>5,0</Coordinates>
        </Tile>
        <Tile AreaType="Path">
            <Coordinates>6,0</Coordinates>
        </Tile>
        <Tile AreaType="Path">
            <Coordinates>7,0</Coordinates>
        </Tile>
        <Tile AreaType="Path">
            <Coordinates>8,0</Coordinates>
        </Tile>
        <Tile AreaType="Path">
            <Coordinates>9,0</Coordinates>
        </Tile>
        <Tile AreaType="Path">
            <Coordinates>9,1</Coordinates>
        </Tile>
        <Tile AreaType="Path">
            <Coordinates>9,2</Coordinates>
        </Tile>
        <Tile AreaType="Path">
            <Coordinates>9,3</Coordinates>
        </Tile>
        <Tile AreaType="Path">
            <Coordinates>10,3</Coordinates>
        </Tile>
        <Tile AreaType="Path">
            <Coordinates>11,3</Coordinates>
        </Tile>
        <Tile AreaType="Path">
            <Coordinates>11,2</Coordinates>
        </Tile>
        <Tile AreaType="GoalArea">
            <Coordinates>11,1</Coordinates>
        </Tile>
        <Tile AreaType="TowerArea">
            <Coordinates>5,2</Coordinates>
        </Tile>
        <Tile AreaType="TowerArea">
            <Coordinates>5,3</Coordinates>
        </Tile>
    </Level1>
</Levels>